energytstoolkit/__init__.py
energytstoolkit/decomposition.py
energytstoolkit/evaluation.py
energytstoolkit/feature_engineering.py
energytstoolkit/lstm.py
energytstoolkit/preprocessing.py
energytstoolkit-0.1.1.dist-info/LICENSE
energytstoolkit-0.1.1.dist-info/METADATA
energytstoolkit-0.1.1.dist-info/WHEEL
energytstoolkit-0.1.1.dist-info/top_level.txt
energytstoolkit-0.1.1.dist-info/RECORD
