Metadata-Version: 2.1
Name: energytstoolkit
Version: 0.1.1
Summary: A toolkit for time series preprocessing, feature engineering, and forecasting
Home-page: https://github.com/AnnaValentinaHirsch/timeseriestoolkit
Author: Anna-Valentina Hirsch
Author-email: a-valentina.hirsch@hotmail.com
Classifier: Programming Language :: Python :: 3
Classifier: License :: OSI Approved :: MIT License
Classifier: Operating System :: OS Independent
Requires-Python: >=3.6
License-File: LICENSE
Requires-Dist: numpy
Requires-Dist: pandas
Requires-Dist: matplotlib
Requires-Dist: statsmodels
Requires-Dist: scikit-learn
Requires-Dist: tensorflow
